summarytools/__init__.py
summarytools/htmlwidgets.py
summarytools/summary.py
summarytools/summarytools.py
summarytools-0.3.0.dist-info/LICENSE.txt
summarytools-0.3.0.dist-info/METADATA
summarytools-0.3.0.dist-info/WHEEL
summarytools-0.3.0.dist-info/top_level.txt
summarytools-0.3.0.dist-info/RECORD
