Metadata-Version: 2.1
Name: summarytools
Version: 0.3.0
Summary: summarytools in jupyter notebook
Home-page: https://github.com/6chaoran/jupyter-summarytools
Author: Liu Chaoran
Author-email: 6chaoran@gmail.com
Project-URL: Bug Reports, https://github.com/6chaoran/jupyter-summarytools/issues
Keywords: sample,setuptools,development
Classifier: Development Status :: 3 - Alpha
Classifier: Intended Audience :: Developers
Classifier: Topic :: Software Development :: Build Tools
Classifier: License :: OSI Approved :: MIT License
Classifier: Programming Language :: Python :: 3
Classifier: Programming Language :: Python :: 3.7
Classifier: Programming Language :: Python :: 3.8
Classifier: Programming Language :: Python :: 3.9
Classifier: Programming Language :: Python :: 3.10
Classifier: Programming Language :: Python :: 3 :: Only
Requires-Python: >=3.6
Provides-Extra: dev
Provides-Extra: test
License-File: LICENSE.txt
